com/__init__.py
com/ilderness/__init__.py
com/ilderness/solo/__init__.py
com/ilderness/solo/model/__init__.py
com/ilderness/solo/model/account_pb2.py
com/ilderness/solo/model/account_pb2.pyi
com/ilderness/solo/model/account_pb2_grpc.py
com/ilderness/solo/service/__init__.py
com/ilderness/solo/service/account_service_pb2.py
com/ilderness/solo/service/account_service_pb2.pyi
com/ilderness/solo/service/account_service_pb2_grpc.py
solo_proto-0.0.2.dist-info/LICENSE
solo_proto-0.0.2.dist-info/METADATA
solo_proto-0.0.2.dist-info/WHEEL
solo_proto-0.0.2.dist-info/top_level.txt
solo_proto-0.0.2.dist-info/RECORD
